h6/__init__.py
h6/cli.py
h6/zoom_h6.py
h6-0.1.1.dist-info/entry_points.txt
h6-0.1.1.dist-info/WHEEL
h6-0.1.1.dist-info/METADATA
h6-0.1.1.dist-info/RECORD
