Metadata-Version: 2.1
Name: h6
Version: 0.1.1
Summary: A Python library to emulate a Zoom H6 recorder remote control
Home-page: https://github.com/mattogodoy/h6/
License: MIT
Keywords: zoom,h6,remote
Author: Matias Godoy
Author-email: mattogodoy@gmail.com
Requires-Python: >=3.6,<4.0
Classifier: License :: OSI Approved :: MIT License
Classifier: Programming Language :: Python :: 3
Classifier: Programming Language :: Python :: 3.6
Classifier: Programming Language :: Python :: 3.7
Classifier: Programming Language :: Python :: 3.8
Classifier: Programming Language :: Python :: 3.9
Requires-Dist: click (>=7.1.2,<8.0.0)
Requires-Dist: pyserial (>=3.5,<4.0)
Project-URL: Repository, https://github.com/mattogodoy/h6/
